cmatcher/LICENSE
cmatcher/README.MD
cmatcher/__init__.py
cmatcher/requirements.txt
cmatcher/thirdparty.json
cmatcher-0.11.dist-info/LICENSE.rst
cmatcher-0.11.dist-info/METADATA
cmatcher-0.11.dist-info/WHEEL
cmatcher-0.11.dist-info/top_level.txt
cmatcher-0.11.dist-info/RECORD
