Metadata-Version: 2.1
Name: cmatcher
Version: 0.11
Summary: Find the best background and foreground color combinations from a given RGB value
Home-page: https://github.com/hansalemaos/cmatcher
Author: Johannes Fischer
Author-email: <aulasparticularesdealemaosp@gmail.com>
License: MIT
Keywords: color,colour,terminalcolor,html,combinations
Classifier: Development Status :: 4 - Beta
Classifier: Programming Language :: Python :: 3 :: Only
Classifier: Programming Language :: Python :: 3.9
Classifier: Topic :: Scientific/Engineering :: Visualization
Classifier: Topic :: Software Development :: Libraries :: Python Modules
Classifier: Topic :: Text Editors :: Text Processing
Classifier: Topic :: Text Processing :: General
Classifier: Topic :: Text Processing :: Indexing
Classifier: Topic :: Text Processing :: Filters
Classifier: Topic :: Utilities
License-File: LICENSE.rst
Requires-Dist: numba
Requires-Dist: numpy
Requires-Dist: pandas
Requires-Dist: sty
